OpenFisca_France_Indirect_Taxation-0.4.dev0.dist-info/DESCRIPTION.rst
OpenFisca_France_Indirect_Taxation-0.4.dev0.dist-info/METADATA
OpenFisca_France_Indirect_Taxation-0.4.dev0.dist-info/RECORD
OpenFisca_France_Indirect_Taxation-0.4.dev0.dist-info/WHEEL
OpenFisca_France_Indirect_Taxation-0.4.dev0.dist-info/metadata.json
OpenFisca_France_Indirect_Taxation-0.4.dev0.dist-info/top_level.txt
openfisca_france_indirect_taxation/__init__.py
openfisca_france_indirect_taxation/entities.py
openfisca_france_indirect_taxation/scenarios.py
openfisca_france_indirect_taxation/surveys.py
openfisca_france_indirect_taxation/almost_ideal_demand_system/__init__.py
openfisca_france_indirect_taxation/almost_ideal_demand_system/aids_dataframe_builder_categ.py
openfisca_france_indirect_taxation/almost_ideal_demand_system/aids_dataframe_builder_coicop.py
openfisca_france_indirect_taxation/almost_ideal_demand_system/aids_estimation.py
openfisca_france_indirect_taxation/almost_ideal_demand_system/aids_estimation_from_stata.py
openfisca_france_indirect_taxation/almost_ideal_demand_system/aids_estimation_new_categ.py
openfisca_france_indirect_taxation/almost_ideal_demand_system/aids_price_index_builder.py
openfisca_france_indirect_taxation/assets/__init__.py
openfisca_france_indirect_taxation/build_survey_data/__init__.py
openfisca_france_indirect_taxation/build_survey_data/run_all.py
openfisca_france_indirect_taxation/build_survey_data/step_03_calage.py
openfisca_france_indirect_taxation/build_survey_data/step_04_homogeneisation_categories_fiscales.py
openfisca_france_indirect_taxation/build_survey_data/step_0_1_1_homogeneisation_donnees_depenses.py
openfisca_france_indirect_taxation/build_survey_data/step_0_1_2_imputations_loyers_proprietaires.py
openfisca_france_indirect_taxation/build_survey_data/step_0_2_homogeneisation_vehicules.py
openfisca_france_indirect_taxation/build_survey_data/step_0_3_homogeneisation_caracteristiques_menages.py
openfisca_france_indirect_taxation/build_survey_data/step_0_4_homogeneisation_revenus_menages.py
openfisca_france_indirect_taxation/build_survey_data/utils.py
openfisca_france_indirect_taxation/example/__init__.py
openfisca_france_indirect_taxation/example/calage_bdf_cn.py
openfisca_france_indirect_taxation/example/calcul_depenses_ticpe.py
openfisca_france_indirect_taxation/example/calcul_quantites_ticpe.py
