Metadata-Version: 2.0
Name: OpenFisca-France-Indirect-Taxation
Version: 0.4.dev0
Summary: France specific indirect taxation model for OpenFisca -- a versatile microsimulation free software
Home-page: https://github.com/openfisca/openfisca-france-indirect-taxation
Author: OpenFisca Team
Author-email: contact@openfisca.fr
License: http://www.fsf.org/licensing/licenses/agpl-3.0.html
Keywords: benefit france indirect microsimulation social tax
Platform: UNKNOWN
Classifier: Development Status :: 2 - Pre-Alpha
Classifier: License :: OSI Approved :: GNU Affero General Public License v3
Classifier: Operating System :: POSIX
Classifier: Programming Language :: Python
Classifier: Topic :: Scientific/Engineering :: Information Analysis
Requires-Dist: Babel (>=0.9.4)
Requires-Dist: Biryani[datetimeconv] (>=0.10.2dev)
Requires-Dist: OpenFisca-Core (>=0.4dev)
Requires-Dist: numpy
Requires-Dist: scipy (>=0.12)
Provides-Extra: tests
Requires-Dist: pandas (>=0.13); extra == 'tests'
